agniscient/__init__.py
agniscient/anonymizer.py
agniscient/anonymizer_exp.py
agniscient/config.py
agniscient/database.py
agniscient/database_exp.py
agniscient/llm_client.py
agniscient/llm_client_exp.py
agniscient-0.1.1.0.3.dist-info/METADATA
agniscient-0.1.1.0.3.dist-info/WHEEL
agniscient-0.1.1.0.3.dist-info/licenses/LICENSE
agniscient-0.1.1.0.3.dist-info/RECORD
