Metadata-Version: 2.4
Name: agniscient
Version: 0.1.1.0.3
Summary: Secure LLM interaction wrapper with PII protection
Project-URL: Homepage, https://github.com/helloHarsh123/SLLM/tree/u/hg/v0/agnisicent
Author: Agniscient
License-File: LICENSE
Requires-Python: >=3.7
Requires-Dist: cryptography
Requires-Dist: faker
Requires-Dist: langchain-experimental
Requires-Dist: openai
Requires-Dist: presidio-analyzer
Requires-Dist: presidio-anonymizer
Requires-Dist: spacy
Requires-Dist: sqlalchemy
